tados_sysnet/__init__.py
tados_sysnet-0.1.0.dist-info/METADATA
tados_sysnet-0.1.0.dist-info/WHEEL
tados_sysnet-0.1.0.dist-info/top_level.txt
tados_sysnet-0.1.0.dist-info/RECORD
